MANIFEST.in
README.md
s3env.py
setup.cfg
setup.py
s3env.egg-info/PKG-INFO
s3env.egg-info/SOURCES.txt
s3env.egg-info/dependency_links.txt
s3env.egg-info/entry_points.txt
s3env.egg-info/requires.txt
s3env.egg-info/top_level.txt