Metadata-Version: 1.0
Name: s3env
Version: 0.0.4
Summary: Manipulate a key/value JSON object file in an S3 bucket through the CLI
Home-page: https://github.com/cameronmaske/s3env
Author: Cameron Maske
Author-email: cameronmaske@gmail.com
License: MIT
Platform: UNKNOWN
